tsdf/__init__.py
tsdf/constants.py
tsdf/file_utils.py
tsdf/legacy_tsdf_utils.py
tsdf/numpy_utils.py
tsdf/parse_metadata.py
tsdf/read_binary.py
tsdf/read_tsdf.py
tsdf/tsdfmetadata.py
tsdf/validator.py
tsdf/write_binary.py
tsdf/write_tsdf.py
tsdf-0.6.1.dist-info/METADATA
tsdf-0.6.1.dist-info/WHEEL
tsdf-0.6.1.dist-info/entry_points.txt
tsdf-0.6.1.dist-info/licenses/LICENSE
tsdf-0.6.1.dist-info/RECORD
