Metadata-Version: 2.4
Name: tsdf
Version: 0.6.1
Summary: A Python library that provides methods for encoding and decoding TSDF (Time Series Data Format) data, which allows you to easily create, manipulate and serialize TSDF files in your Python code.
License: Apache-2.0
License-File: LICENSE
Keywords: Time Series Data Format (TSDF),binary data,digital sensors
Author: Vedran Kasalica
Author-email: v.kaslica@esciencecenter.nl
Requires-Python: >=3.11,<3.13
Classifier: License :: OSI Approved :: Apache Software License
Classifier: Programming Language :: Python
Classifier: Programming Language :: Python :: 3
Classifier: Programming Language :: Python :: 3.11
Classifier: Programming Language :: Python :: 3.12
Requires-Dist: numpy (>=1.24.1,<2.0.0)
Requires-Dist: pandas (>=2.1.3,<3.0.0)
Project-URL: Repository, https://github.com/biomarkersParkinson/tsdf
